{
  "Info": {
    "Class": "clsDbImexSpec",
    "Description": "Import/Export Specification from MSysIMEXSpecs"
  },
  "Items": {
    "DateDelim": "/",
    "DateFourDigitYear": false,
    "DateLeadingZeros": false,
    "DateOrder": 2,
    "DecimalPoint": "",
    "FieldSeparator": "\u0001",
    "FileType": 0,
    "SpecName": "10",
    "SpecType": 0,
    "StartRow": 1,
    "TextDelim": "\u0002",
    "TimeDelim": ":",
    "Columns": {
      "Axle": {
        "Attributes": 0,
        "DataType": 10,
        "IndexType": 0,
        "SkipColumn": false,
        "Start": 128,
        "Width": 5
      },
      "BuildDate": {
        "Attributes": 0,
        "DataType": 8,
        "IndexType": 0,
        "SkipColumn": false,
        "Start": 57,
        "Width": 13
      },
      "Cost": {
        "Attributes": 0,
        "DataType": 5,
        "IndexType": 0,
        "SkipColumn": false,
        "Start": 133,
        "Width": 6
      },
      "Description": {
        "Attributes": 0,
        "DataType": 10,
        "IndexType": 0,
        "SkipColumn": false,
        "Start": 24,
        "Width": 15
      },
      "Grp": {
        "Attributes": 0,
        "DataType": 10,
        "IndexType": 0,
        "SkipColumn": false,
        "Start": 5,
        "Width": 4
      },
      "Make": {
        "Attributes": 0,
        "DataType": 10,
        "IndexType": 0,
        "SkipColumn": false,
        "Start": 76,
        "Width": 9
      },
      "Model": {
        "Attributes": 0,
        "DataType": 10,
        "IndexType": 0,
        "SkipColumn": false,
        "Start": 85,
        "Width": 6
      },
      "MYear": {
        "Attributes": 0,
        "DataType": 7,
        "IndexType": 0,
        "SkipColumn": false,
        "Start": 70,
        "Width": 6
      },
      "PlateNum": {
        "Attributes": 0,
        "DataType": 10,
        "IndexType": 1,
        "SkipColumn": false,
        "Start": 91,
        "Width": 9
      },
      "PlateState": {
        "Attributes": 0,
        "DataType": 10,
        "IndexType": 0,
        "SkipColumn": false,
        "Start": 100,
        "Width": 11
      },
      "Sch": {
        "Attributes": 0,
        "DataType": 10,
        "IndexType": 0,
        "SkipColumn": false,
        "Start": 1,
        "Width": 4
      },
      "SubType": {
        "Attributes": 0,
        "DataType": 10,
        "IndexType": 0,
        "SkipColumn": false,
        "Start": 120,
        "Width": 8
      },
      "UnitID": {
        "Attributes": 0,
        "DataType": 4,
        "IndexType": 1,
        "SkipColumn": false,
        "Start": 9,
        "Width": 7
      },
      "UnitNum": {
        "Attributes": 0,
        "DataType": 10,
        "IndexType": 1,
        "SkipColumn": false,
        "Start": 16,
        "Width": 8
      },
      "UnitType": {
        "Attributes": 0,
        "DataType": 10,
        "IndexType": 0,
        "SkipColumn": false,
        "Start": 111,
        "Width": 9
      },
      "VIN": {
        "Attributes": 0,
        "DataType": 10,
        "IndexType": 0,
        "SkipColumn": false,
        "Start": 39,
        "Width": 18
      }
    }
  }
}
